svc_reg/__init__.py
svc_reg/_core.py
svc_reg/exceptions.py
svc_reg/flask.py
svc_reg/py.typed
svc_reg-23.3.0.dist-info/METADATA
svc_reg-23.3.0.dist-info/WHEEL
svc_reg-23.3.0.dist-info/licenses/LICENSE
svc_reg-23.3.0.dist-info/RECORD
