Metadata-Version: 2.1
Name: svc-reg
Version: 23.3.0
Summary: A Service Registry for Dependency Injection
Project-URL: Changelog, https://github.com/hynek/svc-reg/blob/main/CHANGELOG.md
Project-URL: Documentation, https://github.com/hynek/svc-reg/blob/main/README.md
Project-URL: Source, https://github.com/hynek/svc-reg
Project-URL: Funding, https://github.com/sponsors/hynek
Author-email: Hynek Schlawack <hs@ox.cx>
License-Expression: MIT
License-File: LICENSE
Keywords: dependency injection
Classifier: Development Status :: 4 - Beta
Classifier: License :: OSI Approved :: MIT License
Classifier: Programming Language :: Python :: 3.8
Classifier: Programming Language :: Python :: 3.9
Classifier: Programming Language :: Python :: 3.10
Classifier: Programming Language :: Python :: 3.11
Classifier: Programming Language :: Python :: 3.12
Classifier: Typing :: Typed
Requires-Python: >=3.8
Requires-Dist: attrs
Provides-Extra: dev
Requires-Dist: flask; extra == 'dev'
Requires-Dist: svc-reg[tests,typing]; extra == 'dev'
Requires-Dist: tox>4; extra == 'dev'
Provides-Extra: tests
Requires-Dist: pytest; extra == 'tests'
Requires-Dist: pytest-asyncio; extra == 'tests'
Requires-Dist: sybil; extra == 'tests'
Provides-Extra: typing
Requires-Dist: flask; extra == 'typing'
Requires-Dist: mypy>=1.4; extra == 'typing'
